<?xml version="1.0" encoding="UTF-8"?>
<configuration>
    <!-- Standard Console Logging (so you can still see logs in your IDE) -->
    <appender name="CONSOLE" class="ch.qos.logback.core.ConsoleAppender">
        <encoder>
            <pattern>%d{yyyy-MM-dd HH:mm:ss} [%thread] %-5level %logger{36} - %msg%n</pattern>
        </encoder>
    </appender>

    <!-- Loki Logging Appender -->
    <appender name="LOKI" class="com.github.loki4j.logback.Loki4jAppender">
        <http>
            <url>http://localhost:3100/loki/api/v1/push</url>
        </http>
        <format>
            <label>
                <pattern>app=metropark,host=${HOSTNAME},level=%level</pattern>
            </label>
            <message>
                <pattern>%d{yyyy-MM-dd HH:mm:ss} [%thread] %-5level %logger{36} - %msg%n</pattern>
            </message>
        </format>
    </appender>

    <!-- Attach both appenders to the root logger -->
    <root level="INFO">
        <appender-ref ref="CONSOLE" />
        <appender-ref ref="LOKI" />
    </root>
</configuration>